{"status":"error","publicPath":"http://0.0.0.0:8080/","chunks":{"app":[{"name":"bundle.js","publicPath":"http://0.0.0.0:8080/bundle.js","path":"/home/aliaksandr/Projects/django-trip-app/trip_app/frontend/dist/bundle.js"},{"name":"app.63fcc49f9bbcd95972e2.hot-update.js","publicPath":"http://0.0.0.0:8080/app.63fcc49f9bbcd95972e2.hot-update.js","path":"/home/aliaksandr/Projects/django-trip-app/trip_app/frontend/dist/app.63fcc49f9bbcd95972e2.hot-update.js"}]},"error":"ModuleError","message":"Module Error (from ./node_modules/eslint-loader/index.js):\nerror: Parsing error: Can not use keyword 'await' outside an async function\n\n  21 |       if (this.next) {\n  22 |         this.loadingTrips = true;\n> 23 |         let resp = await apiService(this.next);\n     |                    ^\n  24 |         if (resp.valid){\n  25 |           this.trips.push(...data.results);\n  26 |           this.loadingTrips = false; at src/views/SearchTripList.vue:36:19:\n  34 |       if (this.next) {\n  35 |         this.loadingTrips = true;\n> 36 |         let resp = await apiService(this.next);\n     |                   ^\n  37 |         if (resp.valid){\n  38 |           this.trips.push(...data.results);\n  39 |           this.loadingTrips = false;\n\n\n1 error found."}